POEM/LICENSE
POEM/NOTICE.txt
POEM/README.md
POEM/models/KlemensCallawayModel.m
POEM/models/RateTheory.m
POEM/models/himmelblau.py
POEM/models/lorentzAttractor.py
POEM/models/matyas.py
POEM/models/mishraBirdConstrained.py
POEM/models/model_cal.py
POEM/models/sauq.m
POEM/models/simple.py
POEM/src/__init__.py
POEM/src/_utils.py
POEM/src/main.py
POEM/src/poem/PoemTemplate.py
POEM/src/poem/PoemTemplateInterface.py
POEM/src/poem/__init__.py
POEM/src/poem/plotUtils.py
POEM/src/poem/poemUtils.py
POEM/src/poem/templates/__init__.py
POEM/src/poem/templates/config.toml
POEM/src/poem/templates/raven_template_bayesian_optimization.xml
POEM/src/poem/templates/raven_template_bayesian_optimization_dynamic.xml
POEM/src/poem/templates/raven_template_model_calibration.xml
POEM/src/poem/templates/raven_template_model_calibration_dynamic.xml
POEM/src/poem/templates/raven_template_sampling.xml
POEM/src/poem/templates/raven_template_sampling_dynamic.xml
POEM/src/poem/templates/raven_template_sensitivity.xml
POEM/src/poem/templates/raven_template_sensitivity_dynamic.xml
POEM/src/poem/templates/raven_template_sparse_grid.xml
POEM/src/poem/templates/raven_template_sparse_grid_construction.xml
POEM/src/poem/templates/raven_template_sparse_grid_construction_dynamic.xml
POEM/src/poem/templates/raven_template_sparse_grid_rom.xml
POEM/src/poem/templates/raven_template_sparse_grid_rom_dynamic.xml
POEM/src/poem/templates/raven_template_train_rom.xml
POEM/src/poem/templates/raven_template_train_rom_dynamic.xml
poem_ravenframework-0.1.dist-info/METADATA
poem_ravenframework-0.1.dist-info/WHEEL
poem_ravenframework-0.1.dist-info/entry_points.txt
poem_ravenframework-0.1.dist-info/top_level.txt
poem_ravenframework-0.1.dist-info/RECORD
