Metadata-Version: 2.1
Name: poem-ravenframework
Version: 0.1
Summary: Platform of Optimal Experiment Management
Home-page: https://github.com/idaholab/POEM
Requires-Python: >=3.9
Requires-Dist: raven-framework >=3.0
Requires-Dist: baycal-ravenframework
